mkdocs_monorepo_plugin/__init__.py
mkdocs_monorepo_plugin/edit_uri.py
mkdocs_monorepo_plugin/merger.py
mkdocs_monorepo_plugin/parser.py
mkdocs_monorepo_plugin/plugin.py
mkdocs_monorepo_plugin/tests/__init__.py
mkdocs_monorepo_plugin/tests/test_plugin.py
mkdocs_monorepo_plugin-1.1.2.dist-info/LICENSE
mkdocs_monorepo_plugin-1.1.2.dist-info/METADATA
mkdocs_monorepo_plugin-1.1.2.dist-info/WHEEL
mkdocs_monorepo_plugin-1.1.2.dist-info/entry_points.txt
mkdocs_monorepo_plugin-1.1.2.dist-info/top_level.txt
mkdocs_monorepo_plugin-1.1.2.dist-info/RECORD
