Metadata-Version: 2.1
Name: mkdocs-monorepo-plugin
Version: 1.1.2
Summary: Plugin for adding monorepository support in Mkdocs.
Home-page: https://github.com/backstage/mkdocs-monorepo-plugin
Author: Bilawal Hameed
Author-email: bil@spotify.com
License: Apache-2.0
Keywords: mkdocs monorepo
Platform: UNKNOWN
Classifier: Development Status :: 5 - Production/Stable
Classifier: Intended Audience :: Developers
Classifier: Intended Audience :: Information Technology
Classifier: Programming Language :: Python
Classifier: Programming Language :: Python :: 3 :: Only
Classifier: Programming Language :: Python :: 3.9
Classifier: Programming Language :: Python :: 3.10
Classifier: Programming Language :: Python :: 3.11
Classifier: Programming Language :: Python :: 3.12
Requires-Python: >=3.9
License-File: LICENSE
Requires-Dist: mkdocs>=1.0.4
Requires-Dist: python-slugify>=4.0.1
